sqlalchemy_cloudflare_d1/__init__.py
sqlalchemy_cloudflare_d1/compiler.py
sqlalchemy_cloudflare_d1/connection.py
sqlalchemy_cloudflare_d1/dialect.py
sqlalchemy_cloudflare_d1/dialect_async.py
sqlalchemy_cloudflare_d1/py.typed
sqlalchemy_cloudflare_d1-0.3.5.dist-info/METADATA
sqlalchemy_cloudflare_d1-0.3.5.dist-info/WHEEL
sqlalchemy_cloudflare_d1-0.3.5.dist-info/entry_points.txt
sqlalchemy_cloudflare_d1-0.3.5.dist-info/licenses/LICENSE
sqlalchemy_cloudflare_d1-0.3.5.dist-info/RECORD
