Metadata-Version: 2.4
Name: sqlalchemy-cloudflare-d1
Version: 0.3.5
Summary: A SQLAlchemy dialect for Cloudflare's D1 Serverless SQLite Database
Project-URL: Homepage, https://github.com/collierking/sqlalchemy-cloudflare-d1
Project-URL: Repository, https://github.com/collierking/sqlalchemy-cloudflare-d1
Project-URL: Issues, https://github.com/collierking/sqlalchemy-cloudflare-d1/issues
Author: Collier King
License: MIT License
License-File: LICENSE
Keywords: cloudflare,d1,database,serverless,sqlalchemy,sqlite
Classifier: Development Status :: 3 - Alpha
Classifier: Intended Audience :: Developers
Classifier: License :: OSI Approved :: MIT License
Classifier: Programming Language :: Python :: 3
Classifier: Programming Language :: Python :: 3.9
Classifier: Programming Language :: Python :: 3.10
Classifier: Programming Language :: Python :: 3.11
Classifier: Programming Language :: Python :: 3.12
Classifier: Topic :: Database
Classifier: Topic :: Database :: Front-Ends
Classifier: Topic :: Software Development :: Libraries :: Python Modules
Requires-Python: >=3.9
Requires-Dist: httpx>=0.24.0
Requires-Dist: sqlalchemy>=2.0.0
Requires-Dist: typing-extensions>=4.0.0
Provides-Extra: async
Requires-Dist: greenlet>=3.2.3; extra == 'async'
Provides-Extra: dev
Requires-Dist: black>=23.0.0; extra == 'dev'
Requires-Dist: isort>=5.12.0; extra == 'dev'
Requires-Dist: mypy>=1.0.0; extra == 'dev'
Requires-Dist: pytest-asyncio>=0.21.0; extra == 'dev'
Requires-Dist: pytest>=7.0.0; extra == 'dev'
Requires-Dist: ruff>=0.0.280; extra == 'dev'
